clfpy/__init__.py
clfpy/auth_client.py
clfpy/gss_client.py
clfpy/hpc_client.py
clfpy/services_client.py
clfpy/soap_client.py
clfpy/tools.py
clfpy/wfm_client.py
clfpy/cli/__init__.py
clfpy/cli/cli_auth.py
clfpy/cli/cli_gss.py
clfpy/cli/cli_images.py
clfpy/cli/cli_services.py
clfpy/cli/tools.py
clfpy-1.3.2.data/scripts/clfpy_cli
clfpy-1.3.2.dist-info/LICENSE.txt
clfpy-1.3.2.dist-info/METADATA
clfpy-1.3.2.dist-info/WHEEL
clfpy-1.3.2.dist-info/top_level.txt
clfpy-1.3.2.dist-info/RECORD
