Metadata-Version: 2.1
Name: clfpy
Version: 1.3.2
Summary: Library for accessing infrastructure services in SemWES and its derivatives
Home-page: https://github.com/CloudiFacturing/clfpy
Author: Robert Schittny
Author-email: robert.schittny@sintef.no
License: UNKNOWN
Platform: UNKNOWN
Classifier: Development Status :: 5 - Production/Stable
Classifier: Programming Language :: Python :: 2.7
Classifier: Programming Language :: Python :: 3
Requires-Python: >=2.7, <4
Requires-Dist: requests
Requires-Dist: suds-jurko
Requires-Dist: future
Requires-Dist: future-fstrings
